my_lib.py
my_lib_my-0.0.1.dist-info/METADATA
my_lib_my-0.0.1.dist-info/WHEEL
my_lib_my-0.0.1.dist-info/top_level.txt
my_lib_my-0.0.1.dist-info/RECORD
